imperial_materials_simulation/__init__.py
imperial_materials_simulation/display.py
imperial_materials_simulation/main.py
imperial_materials_simulation/physics.py
imperial_materials_simulation-1.3.3.dist-info/METADATA
imperial_materials_simulation-1.3.3.dist-info/WHEEL
imperial_materials_simulation-1.3.3.dist-info/licenses/LICENSE
imperial_materials_simulation-1.3.3.dist-info/RECORD
