Metadata-Version: 2.4
Name: imperial-materials-simulation
Version: 1.3.3
Summary: Molecular simulation tool made for ICL materials students
License-File: LICENSE
Requires-Python: >=3.9
Requires-Dist: ipykernel>=6.29.5
Requires-Dist: ipympl>=0.9.6
Requires-Dist: ipywidgets>=8.1.5
Requires-Dist: matplotlib>=3.9.4
Requires-Dist: numba>=0.60.0
Requires-Dist: numpy>=2.0.2
Requires-Dist: pandas>=2.2.3
Requires-Dist: py3dmol>=2.4.2
Requires-Dist: scipy>=1.13.1
Requires-Dist: xlsxwriter>=3.2.9
